cologger.py
util.py
cologger-0.0.1.dist-info/LICENSE
cologger-0.0.1.dist-info/METADATA
cologger-0.0.1.dist-info/WHEEL
cologger-0.0.1.dist-info/top_level.txt
cologger-0.0.1.dist-info/RECORD
